{"content":{"settings":"{\n    \"python.linting.pylintEnabled\": false,\n    \"python.linting.flake8Enabled\": true,\n    \"python.linting.enabled\": true,\n    \"python.formatting.provider\": \"yapf\"\n}","tasks":"{}","launch":"{\n    // Use IntelliSense to learn about possible attributes.\n    // Hover to view descriptions of existing attributes.\n    // For more information, visit: https://go.microsoft.com/fwlink/?linkid=830387\n    \"version\": \"0.2.0\",\n    \"configurations\": [\n        {\n            \"name\": \"Python: Current File\",\n            \"type\": \"python\",\n            \"request\": \"launch\",\n            \"program\": \"${file}\",\n            \"console\": \"integratedTerminal\"\n        }\n    ]\n}"}}